alphatrade/__init__.py
alphatrade/alphatrade.py
alphatrade/exceptions.py
alphatrade-1.0.0.dist-info/LICENSE
alphatrade-1.0.0.dist-info/METADATA
alphatrade-1.0.0.dist-info/WHEEL
alphatrade-1.0.0.dist-info/top_level.txt
alphatrade-1.0.0.dist-info/RECORD
