Metadata-Version: 2.1
Name: alphatrade
Version: 1.0.0
Summary: Python APIs for SAS Online Alpha Trade Web Platform
Home-page: https://github.com/algo2t/alphatrade
Author: Algo 2 Trade
Author-email: help@algo2.trade
License: UNKNOWN
Keywords: alphatrade,alpha-trade,sasonline,python,sdk,trading,stock markets
Platform: UNKNOWN
Classifier: Development Status :: 5 - Production/Stable
Classifier: Intended Audience :: Developers
Classifier: Intended Audience :: Financial and Insurance Industry
Classifier: Natural Language :: English
Classifier: Operating System :: OS Independent
Classifier: License :: OSI Approved :: MIT License
Classifier: Programming Language :: Python :: 3.8
Classifier: Programming Language :: Python :: 3.9
Classifier: Programming Language :: Python :: 3.10
Classifier: Programming Language :: Python :: 3.11
Classifier: Programming Language :: Python :: Implementation :: PyPy
Classifier: Topic :: Software Development :: Libraries :: Python Modules
Classifier: Topic :: Software Development :: Libraries
Requires-Python: >=3.7
License-File: LICENSE
Requires-Dist: setuptools (==57.5.0)
Requires-Dist: requests
Requires-Dist: websocket-client
Requires-Dist: protlib
Requires-Dist: pandas
Requires-Dist: pyotp
